montreal_forced_aligner/__init__.py
montreal_forced_aligner/__main__.py
montreal_forced_aligner/_version.py
montreal_forced_aligner/abc.py
montreal_forced_aligner/config.py
montreal_forced_aligner/data.py
montreal_forced_aligner/db.py
montreal_forced_aligner/exceptions.py
montreal_forced_aligner/helper.py
montreal_forced_aligner/models.py
montreal_forced_aligner/textgrid.py
montreal_forced_aligner/utils.py
montreal_forced_aligner/acoustic_modeling/__init__.py
montreal_forced_aligner/acoustic_modeling/base.py
montreal_forced_aligner/acoustic_modeling/lda.py
montreal_forced_aligner/acoustic_modeling/monophone.py
montreal_forced_aligner/acoustic_modeling/pronunciation_probabilities.py
montreal_forced_aligner/acoustic_modeling/sat.py
montreal_forced_aligner/acoustic_modeling/trainer.py
montreal_forced_aligner/acoustic_modeling/triphone.py
montreal_forced_aligner/alignment/__init__.py
montreal_forced_aligner/alignment/adapting.py
montreal_forced_aligner/alignment/base.py
montreal_forced_aligner/alignment/mixins.py
montreal_forced_aligner/alignment/multiprocessing.py
montreal_forced_aligner/alignment/pretrained.py
montreal_forced_aligner/command_line/__init__.py
montreal_forced_aligner/command_line/adapt.py
montreal_forced_aligner/command_line/align.py
montreal_forced_aligner/command_line/align_one.py
montreal_forced_aligner/command_line/anchor.py
montreal_forced_aligner/command_line/configure.py
montreal_forced_aligner/command_line/create_segments.py
montreal_forced_aligner/command_line/diarize_speakers.py
montreal_forced_aligner/command_line/find_oovs.py
montreal_forced_aligner/command_line/g2p.py
montreal_forced_aligner/command_line/history.py
montreal_forced_aligner/command_line/mfa.py
montreal_forced_aligner/command_line/model.py
montreal_forced_aligner/command_line/remap.py
montreal_forced_aligner/command_line/server.py
montreal_forced_aligner/command_line/tokenize.py
montreal_forced_aligner/command_line/train_acoustic_model.py
montreal_forced_aligner-3.3.6.dist-info/licenses/LICENSE
montreal_forced_aligner-3.3.6.dist-info/METADATA
montreal_forced_aligner-3.3.6.dist-info/WHEEL
montreal_forced_aligner-3.3.6.dist-info/entry_points.txt
montreal_forced_aligner-3.3.6.dist-info/top_level.txt
montreal_forced_aligner-3.3.6.dist-info/RECORD
