Metadata-Version: 2.4
Name: Montreal_Forced_Aligner
Version: 3.3.6
Summary: Montreal Forced Aligner is a package for aligning speech corpora using Kaldi functionality.
Home-page: https://github.com/MontrealCorpusTools/Montreal-Forced-Aligner
Author: Montreal Corpus Tools
Author-email: michael.e.mcauliffe@gmail.com
Maintainer: Michael McAuliffe
Maintainer-email: michael.e.mcauliffe@gmail.com
License: MIT
Keywords: phonology,corpus,phonetics,alignment,segmentation,transcription,g2p,language modeling
Classifier: Development Status :: 3 - Alpha
Classifier: License :: OSI Approved :: MIT License
Classifier: Operating System :: OS Independent
Classifier: Programming Language :: Python
Classifier: Programming Language :: Python :: 3
Classifier: Programming Language :: Python :: 3 :: Only
Classifier: Programming Language :: Python :: Implementation :: CPython
Classifier: Topic :: Multimedia :: Sound/Audio :: Speech
Classifier: Topic :: Scientific/Engineering
Classifier: Topic :: Text Processing :: Linguistic
Requires-Python: >=3.8
License-File: LICENSE
Requires-Dist: click
Requires-Dist: dataclassy
Requires-Dist: kneed
Requires-Dist: librosa
Requires-Dist: matplotlib
Requires-Dist: numpy
Requires-Dist: praatio>=6.0.0
Requires-Dist: pyyaml
Requires-Dist: requests
Requires-Dist: rich
Requires-Dist: rich-click
Requires-Dist: scikit-learn
Requires-Dist: seaborn
Requires-Dist: sqlalchemy>=1.4
Requires-Dist: tqdm
Provides-Extra: anchor
Requires-Dist: anchor-annotator; extra == "anchor"
Requires-Dist: pyqtgraph; extra == "anchor"
Requires-Dist: pyside6; extra == "anchor"
Provides-Extra: dev
Requires-Dist: coverage; extra == "dev"
Requires-Dist: coveralls; extra == "dev"
Requires-Dist: interrogate; extra == "dev"
Requires-Dist: pytest; extra == "dev"
Requires-Dist: pytest-mypy; extra == "dev"
Requires-Dist: setuptools-scm; extra == "dev"
Requires-Dist: tomli; extra == "dev"
Requires-Dist: tox; extra == "dev"
Requires-Dist: tox-conda; extra == "dev"
Provides-Extra: docs
Requires-Dist: interrogate; extra == "docs"
Requires-Dist: numpydoc; extra == "docs"
Requires-Dist: pydata-sphinx-theme; extra == "docs"
Requires-Dist: sphinx; extra == "docs"
Requires-Dist: sphinx-click; extra == "docs"
Requires-Dist: sphinx-design; extra == "docs"
Provides-Extra: testing
Requires-Dist: coverage; extra == "testing"
Requires-Dist: coveralls; extra == "testing"
Requires-Dist: pytest; extra == "testing"
Requires-Dist: pytest-mypy; extra == "testing"
Dynamic: license-file
